[{"GAME_ID":"0028300816","TEAM_ID":1610612741,"TEAM_ABBREVIATION":"CHI","TEAM_CITY":"Chicago","PLAYER_ID":76453,"PLAYER_NAME":"Dave Corzine","NICKNAME":"Dave","START_POSITION":"","COMMENT":"","MIN":31,"FGM":3,"FGA":9,"FG_PCT":0.333,"FG3M":0,"FG3A":0,"FG3_PCT":0.0,"FTM":0,"FTA":0,"FT_PCT":0.0,"OREB":1,"DREB":6,"REB":7,"AST":4,"STL":1,"BLK":2,"TO":0,"PF":2,"PTS":6,"PLUS_MINUS":null},{"GAME_ID":"0028300816","TEAM_ID":1610612741,"TEAM_ABBREVIATION":"CHI","TEAM_CITY":"Chicago","PLAYER_ID":76881,"PLAYER_NAME":"David Greenwood","NICKNAME":"David","START_POSITION":"","COMMENT":"","MIN":33,"FGM":4,"FGA":10,"FG_PCT":0.4,"FG3M":0,"FG3A":0,"FG3_PCT":0.0,"FTM":2,"FTA":2,"FT_PCT":1.0,"OREB":1,"DREB":9,"REB":10,"AST":0,"STL":1,"BLK":1,"TO":1,"PF":6,"PTS":10,"PLUS_MINUS":null},{"GAME_ID":"0028300816","TEAM_ID":1610612741,"TEAM_ABBREVIATION":"CHI","TEAM_CITY":"Chicago","PLAYER_ID":941,"PLAYER_NAME":"Ennis Whatley","NICKNAME":"Ennis","START_POSITION":"","COMMENT":"","MIN":20,"FGM":2,"FGA":5,"FG_PCT":0.4,"FG3M":0,"FG3A":0,"FG3_PCT":0.0,"FTM":1,"FTA":2,"FT_PCT":0.5,"OREB":1,"DREB":3,"REB":4,"AST":6,"STL":0,"BLK":0,"TO":0,"PF":1,"PTS":5,"PLUS_MINUS":null},{"GAME_ID":"0028300816","TEAM_ID":1610612741,"TEAM_ABBREVIATION":"CHI","TEAM_CITY":"Chicago","PLAYER_ID":78523,"PLAYER_NAME":"Mitchell Wiggins","NICKNAME":"Mitchell","START_POSITION":"","COMMENT":"","MIN":23,"FGM":5,"FGA":11,"FG_PCT":0.455,"FG3M":0,"FG3A":0,"FG3_PCT":0.0,"FTM":1,"FTA":1,"FT_PCT":1.0,"OREB":9,"DREB":1,"REB":10,"AST":3,"STL":1,"BLK":1,"TO":1,"PF":6,"PTS":11,"PLUS_MINUS":null},{"GAME_ID":"0028300816","TEAM_ID":1610612741,"TEAM_ABBREVIATION":"CHI","TEAM_CITY":"Chicago","PLAYER_ID":78615,"PLAYER_NAME":"Orlando Woolridge","NICKNAME":"Orlando","START_POSITION":"","COMMENT":"","MIN":41,"FGM":9,"FGA":21,"FG_PCT":0.428,"FG3M":1,"FG3A":1,"FG3_PCT":1.0,"FTM":3,"FTA":3,"FT_PCT":1.0,"OREB":2,"DREB":0,"REB":2,"AST":1,"STL":0,"BLK":0,"TO":3,"PF":2,"PTS":22,"PLUS_MINUS":null},{"GAME_ID":"0028300816","TEAM_ID":1610612741,"TEAM_ABBREVIATION":"CHI","TEAM_CITY":"Chicago","PLAYER_ID":76497,"PLAYER_NAME":"Quintin Dailey","NICKNAME":"Quintin","START_POSITION":"","COMMENT":"","MIN":36,"FGM":9,"FGA":19,"FG_PCT":0.473,"FG3M":0,"FG3A":1,"FG3_PCT":0.0,"FTM":3,"FTA":7,"FT_PCT":0.428,"OREB":1,"DREB":0,"REB":1,"AST":2,"STL":0,"BLK":0,"TO":8,"PF":2,"PTS":21,"PLUS_MINUS":null},{"GAME_ID":"0028300816","TEAM_ID":1610612741,"TEAM_ABBREVIATION":"CHI","TEAM_CITY":"Chicago","PLAYER_ID":77019,"PLAYER_NAME":"Rod Higgins","NICKNAME":"Rod","START_POSITION":"","COMMENT":"","MIN":16,"FGM":2,"FGA":4,"FG_PCT":0.5,"FG3M":0,"FG3A":0,"FG3_PCT":0.0,"FTM":0,"FTA":0,"FT_PCT":0.0,"OREB":0,"DREB":3,"REB":3,"AST":4,"STL":1,"BLK":0,"TO":0,"PF":2,"PTS":4,"PLUS_MINUS":null},{"GAME_ID":"0028300816","TEAM_ID":1610612741,"TEAM_ABBREVIATION":"CHI","TEAM_CITY":"Chicago","PLAYER_ID":77373,"PLAYER_NAME":"Ronnie Lester","NICKNAME":"Ronnie","START_POSITION":"","COMMENT":"","MIN":17,"FGM":3,"FGA":5,"FG_PCT":0.599,"FG3M":0,"FG3A":0,"FG3_PCT":0.0,"FTM":1,"FTA":1,"FT_PCT":1.0,"OREB":0,"DREB":1,"REB":1,"AST":5,"STL":0,"BLK":0,"TO":1,"PF":0,"PTS":7,"PLUS_MINUS":null},{"GAME_ID":"0028300816","TEAM_ID":1610612741,"TEAM_ABBREVIATION":"CHI","TEAM_CITY":"Chicago","PLAYER_ID":77134,"PLAYER_NAME":"Steve Johnson","NICKNAME":"Steve","START_POSITION":"","COMMENT":"","MIN":23,"FGM":4,"FGA":8,"FG_PCT":0.5,"FG3M":0,"FG3A":0,"FG3_PCT":0.0,"FTM":5,"FTA":5,"FT_PCT":1.0,"OREB":3,"DREB":3,"REB":6,"AST":1,"STL":2,"BLK":0,"TO":4,"PF":3,"PTS":13,"PLUS_MINUS":null},{"GAME_ID":"0028300816","TEAM_ID":1610612754,"TEAM_ABBREVIATION":"IND","TEAM_CITY":"Indiana","PLAYER_ID":78250,"PLAYER_NAME":"Brook Steppe","NICKNAME":"Brook","START_POSITION":"","COMMENT":"","MIN":11,"FGM":3,"FGA":5,"FG_PCT":0.599,"FG3M":0,"FG3A":0,"FG3_PCT":0.0,"FTM":0,"FTA":0,"FT_PCT":0.0,"OREB":0,"DREB":0,"REB":0,"AST":0,"STL":0,"BLK":0,"TO":2,"PF":0,"PTS":6,"PLUS_MINUS":null},{"GAME_ID":"0028300816","TEAM_ID":1610612754,"TEAM_ABBREVIATION":"IND","TEAM_CITY":"Indiana","PLAYER_ID":76355,"PLAYER_NAME":"Butch Carter","NICKNAME":"Butch","START_POSITION":"","COMMENT":"","MIN":33,"FGM":10,"FGA":17,"FG_PCT":0.587,"FG3M":0,"FG3A":1,"FG3_PCT":0.0,"FTM":2,"FTA":2,"FT_PCT":1.0,"OREB":0,"DREB":0,"REB":0,"AST":2,"STL":1,"BLK":1,"TO":3,"PF":3,"PTS":22,"PLUS_MINUS":null},{"GAME_ID":"0028300816","TEAM_ID":1610612754,"TEAM_ABBREVIATION":"IND","TEAM_CITY":"Indiana","PLAYER_ID":77236,"PLAYER_NAME":"Clark Kellogg","NICKNAME":"Clark","START_POSITION":"","COMMENT":"","MIN":36,"FGM":7,"FGA":13,"FG_PCT":0.538,"FG3M":0,"FG3A":0,"FG3_PCT":0.0,"FTM":11,"FTA":11,"FT_PCT":1.0,"OREB":3,"DREB":9,"REB":12,"AST":5,"STL":3,"BLK":1,"TO":4,"PF":2,"PTS":25,"PLUS_MINUS":null},{"GAME_ID":"0028300816","TEAM_ID":1610612754,"TEAM_ABBREVIATION":"IND","TEAM_CITY":"Indiana","PLAYER_ID":77148,"PLAYER_NAME":"George Johnson","NICKNAME":"George","START_POSITION":"","COMMENT":"","MIN":36,"FGM":3,"FGA":7,"FG_PCT":0.428,"FG3M":0,"FG3A":0,"FG3_PCT":0.0,"FTM":2,"FTA":3,"FT_PCT":0.667,"OREB":1,"DREB":9,"REB":10,"AST":4,"STL":1,"BLK":1,"TO":1,"PF":4,"PTS":8,"PLUS_MINUS":null},{"GAME_ID":"0028300816","TEAM_ID":1610612754,"TEAM_ABBREVIATION":"IND","TEAM_CITY":"Indiana","PLAYER_ID":78430,"PLAYER_NAME":"Granville Waiters","NICKNAME":"Granville","START_POSITION":"","COMMENT":"","MIN":4,"FGM":0,"FGA":0,"FG_PCT":0.0,"FG3M":0,"FG3A":0,"FG3_PCT":0.0,"FTM":0,"FTA":0,"FT_PCT":0.0,"OREB":0,"DREB":1,"REB":1,"AST":0,"STL":0,"BLK":0,"TO":0,"PF":1,"PTS":0,"PLUS_MINUS":null},{"GAME_ID":"0028300816","TEAM_ID":1610612754,"TEAM_ABBREVIATION":"IND","TEAM_CITY":"Indiana","PLAYER_ID":1006,"PLAYER_NAME":"Herb Williams","NICKNAME":"Herb","START_POSITION":"","COMMENT":"","MIN":25,"FGM":3,"FGA":8,"FG_PCT":0.375,"FG3M":0,"FG3A":0,"FG3_PCT":0.0,"FTM":2,"FTA":4,"FT_PCT":0.5,"OREB":2,"DREB":4,"REB":6,"AST":3,"STL":0,"BLK":0,"TO":3,"PF":0,"PTS":8,"PLUS_MINUS":null},{"GAME_ID":"0028300816","TEAM_ID":1610612754,"TEAM_ABBREVIATION":"IND","TEAM_CITY":"Indiana","PLAYER_ID":78146,"PLAYER_NAME":"Jerry Sichting","NICKNAME":"Jerry","START_POSITION":"","COMMENT":"","MIN":26,"FGM":3,"FGA":6,"FG_PCT":0.5,"FG3M":0,"FG3A":0,"FG3_PCT":0.0,"FTM":1,"FTA":2,"FT_PCT":0.5,"OREB":0,"DREB":0,"REB":0,"AST":4,"STL":0,"BLK":0,"TO":1,"PF":2,"PTS":7,"PLUS_MINUS":null},{"GAME_ID":"0028300816","TEAM_ID":1610612754,"TEAM_ABBREVIATION":"IND","TEAM_CITY":"Indiana","PLAYER_ID":78320,"PLAYER_NAME":"Jim Thomas","NICKNAME":"Jim","START_POSITION":"","COMMENT":"","MIN":4,"FGM":1,"FGA":2,"FG_PCT":0.5,"FG3M":0,"FG3A":0,"FG3_PCT":0.0,"FTM":0,"FTA":0,"FT_PCT":0.0,"OREB":0,"DREB":0,"REB":0,"AST":0,"STL":0,"BLK":0,"TO":0,"PF":0,"PTS":2,"PLUS_MINUS":null},{"GAME_ID":"0028300816","TEAM_ID":1610612754,"TEAM_ABBREVIATION":"IND","TEAM_CITY":"Indiana","PLAYER_ID":77541,"PLAYER_NAME":"Kevin McKenna","NICKNAME":"Kevin","START_POSITION":"","COMMENT":"","MIN":7,"FGM":0,"FGA":2,"FG_PCT":0.0,"FG3M":0,"FG3A":0,"FG3_PCT":0.0,"FTM":2,"FTA":2,"FT_PCT":1.0,"OREB":1,"DREB":0,"REB":1,"AST":0,"STL":1,"BLK":0,"TO":1,"PF":1,"PTS":2,"PLUS_MINUS":null},{"GAME_ID":"0028300816","TEAM_ID":1610612754,"TEAM_ABBREVIATION":"IND","TEAM_CITY":"Indiana","PLAYER_ID":77415,"PLAYER_NAME":"Sidney Lowe","NICKNAME":"Sidney","START_POSITION":"","COMMENT":"","MIN":22,"FGM":3,"FGA":4,"FG_PCT":0.75,"FG3M":0,"FG3A":0,"FG3_PCT":0.0,"FTM":0,"FTA":0,"FT_PCT":0.0,"OREB":1,"DREB":2,"REB":3,"AST":5,"STL":1,"BLK":0,"TO":1,"PF":3,"PTS":6,"PLUS_MINUS":null},{"GAME_ID":"0028300816","TEAM_ID":1610612754,"TEAM_ABBREVIATION":"IND","TEAM_CITY":"Indiana","PLAYER_ID":78257,"PLAYER_NAME":"Steve Stipanovich","NICKNAME":"Steve","START_POSITION":"","COMMENT":"","MIN":36,"FGM":7,"FGA":13,"FG_PCT":0.538,"FG3M":0,"FG3A":0,"FG3_PCT":0.0,"FTM":2,"FTA":2,"FT_PCT":1.0,"OREB":2,"DREB":5,"REB":7,"AST":1,"STL":1,"BLK":0,"TO":3,"PF":3,"PTS":16,"PLUS_MINUS":null}]