[{"GAME_ID":"0029600244","TEAM_ID":1610612746,"TEAM_ABBREVIATION":"LAC","TEAM_CITY":"Los Angeles","PLAYER_ID":919,"PLAYER_NAME":"Loy Vaught","NICKNAME":"Loy","START_POSITION":"F","COMMENT":"","MIN":"40:24","FGM":9.0,"FGA":18.0,"FG_PCT":0.5,"FG3M":0.0,"FG3A":1.0,"FG3_PCT":0.0,"FTM":1.0,"FTA":1.0,"FT_PCT":1.0,"OREB":3.0,"DREB":11.0,"REB":14.0,"AST":3.0,"STL":0.0,"BLK":0.0,"TO":2.0,"PF":3.0,"PTS":19.0,"PLUS_MINUS":-13.0},{"GAME_ID":"0029600244","TEAM_ID":1610612746,"TEAM_ABBREVIATION":"LAC","TEAM_CITY":"Los Angeles","PLAYER_ID":915,"PLAYER_NAME":"Rodney Rogers","NICKNAME":"Rodney","START_POSITION":"F","COMMENT":"","MIN":"36:15","FGM":7.0,"FGA":15.0,"FG_PCT":0.467,"FG3M":1.0,"FG3A":2.0,"FG3_PCT":0.5,"FTM":0.0,"FTA":0.0,"FT_PCT":0.0,"OREB":3.0,"DREB":2.0,"REB":5.0,"AST":1.0,"STL":2.0,"BLK":1.0,"TO":3.0,"PF":3.0,"PTS":15.0,"PLUS_MINUS":-14.0},{"GAME_ID":"0029600244","TEAM_ID":1610612746,"TEAM_ABBREVIATION":"LAC","TEAM_CITY":"Los Angeles","PLAYER_ID":953,"PLAYER_NAME":"Lorenzen Wright","NICKNAME":"Lorenzen","START_POSITION":"C","COMMENT":"","MIN":"27:13","FGM":5.0,"FGA":8.0,"FG_PCT":0.625,"FG3M":0.0,"FG3A":0.0,"FG3_PCT":0.0,"FTM":4.0,"FTA":5.0,"FT_PCT":0.8,"OREB":3.0,"DREB":3.0,"REB":6.0,"AST":2.0,"STL":1.0,"BLK":0.0,"TO":1.0,"PF":0.0,"PTS":14.0,"PLUS_MINUS":-9.0},{"GAME_ID":"0029600244","TEAM_ID":1610612746,"TEAM_ABBREVIATION":"LAC","TEAM_CITY":"Los Angeles","PLAYER_ID":143,"PLAYER_NAME":"Terry Dehere","NICKNAME":"Terry","START_POSITION":"G","COMMENT":"","MIN":"22:12","FGM":1.0,"FGA":5.0,"FG_PCT":0.2,"FG3M":1.0,"FG3A":3.0,"FG3_PCT":0.333,"FTM":0.0,"FTA":0.0,"FT_PCT":0.0,"OREB":0.0,"DREB":1.0,"REB":1.0,"AST":3.0,"STL":0.0,"BLK":0.0,"TO":3.0,"PF":3.0,"PTS":3.0,"PLUS_MINUS":-11.0},{"GAME_ID":"0029600244","TEAM_ID":1610612746,"TEAM_ABBREVIATION":"LAC","TEAM_CITY":"Los Angeles","PLAYER_ID":71,"PLAYER_NAME":"Pooh Richardson","NICKNAME":"Pooh","START_POSITION":"G","COMMENT":"","MIN":"35:27","FGM":7.0,"FGA":10.0,"FG_PCT":0.7,"FG3M":4.0,"FG3A":5.0,"FG3_PCT":0.8,"FTM":2.0,"FTA":2.0,"FT_PCT":1.0,"OREB":0.0,"DREB":3.0,"REB":3.0,"AST":6.0,"STL":1.0,"BLK":0.0,"TO":3.0,"PF":1.0,"PTS":20.0,"PLUS_MINUS":-10.0},{"GAME_ID":"0029600244","TEAM_ID":1610612746,"TEAM_ABBREVIATION":"LAC","TEAM_CITY":"Los Angeles","PLAYER_ID":441,"PLAYER_NAME":"Lamond Murray","NICKNAME":"Lamond","START_POSITION":"","COMMENT":"","MIN":"22:47","FGM":2.0,"FGA":8.0,"FG_PCT":0.25,"FG3M":0.0,"FG3A":2.0,"FG3_PCT":0.0,"FTM":2.0,"FTA":2.0,"FT_PCT":1.0,"OREB":2.0,"DREB":2.0,"REB":4.0,"AST":1.0,"STL":2.0,"BLK":2.0,"TO":1.0,"PF":0.0,"PTS":6.0,"PLUS_MINUS":-10.0},{"GAME_ID":"0029600244","TEAM_ID":1610612746,"TEAM_ABBREVIATION":"LAC","TEAM_CITY":"Los Angeles","PLAYER_ID":699,"PLAYER_NAME":"Brent Barry","NICKNAME":"Brent","START_POSITION":"","COMMENT":"","MIN":"25:48","FGM":6.0,"FGA":15.0,"FG_PCT":0.4,"FG3M":1.0,"FG3A":5.0,"FG3_PCT":0.2,"FTM":4.0,"FTA":4.0,"FT_PCT":1.0,"OREB":2.0,"DREB":0.0,"REB":2.0,"AST":0.0,"STL":2.0,"BLK":1.0,"TO":0.0,"PF":1.0,"PTS":17.0,"PLUS_MINUS":-7.0},{"GAME_ID":"0029600244","TEAM_ID":1610612746,"TEAM_ABBREVIATION":"LAC","TEAM_CITY":"Los Angeles","PLAYER_ID":448,"PLAYER_NAME":"Bo Outlaw","NICKNAME":"Bo","START_POSITION":"","COMMENT":"","MIN":"11:40","FGM":1.0,"FGA":1.0,"FG_PCT":1.0,"FG3M":0.0,"FG3A":0.0,"FG3_PCT":0.0,"FTM":0.0,"FTA":0.0,"FT_PCT":0.0,"OREB":3.0,"DREB":2.0,"REB":5.0,"AST":0.0,"STL":0.0,"BLK":0.0,"TO":1.0,"PF":2.0,"PTS":2.0,"PLUS_MINUS":-3.0},{"GAME_ID":"0029600244","TEAM_ID":1610612746,"TEAM_ABBREVIATION":"LAC","TEAM_CITY":"Los Angeles","PLAYER_ID":239,"PLAYER_NAME":"Darrick Martin","NICKNAME":"Darrick","START_POSITION":"","COMMENT":"","MIN":"12:33","FGM":0.0,"FGA":2.0,"FG_PCT":0.0,"FG3M":0.0,"FG3A":2.0,"FG3_PCT":0.0,"FTM":0.0,"FTA":0.0,"FT_PCT":0.0,"OREB":0.0,"DREB":0.0,"REB":0.0,"AST":1.0,"STL":0.0,"BLK":0.0,"TO":4.0,"PF":0.0,"PTS":0.0,"PLUS_MINUS":-8.0},{"GAME_ID":"0029600244","TEAM_ID":1610612746,"TEAM_ABBREVIATION":"LAC","TEAM_CITY":"Los Angeles","PLAYER_ID":404,"PLAYER_NAME":"Kevin Duckworth","NICKNAME":"Kevin","START_POSITION":"","COMMENT":"","MIN":"5:41","FGM":0.0,"FGA":1.0,"FG_PCT":0.0,"FG3M":0.0,"FG3A":0.0,"FG3_PCT":0.0,"FTM":0.0,"FTA":0.0,"FT_PCT":0.0,"OREB":0.0,"DREB":0.0,"REB":0.0,"AST":0.0,"STL":0.0,"BLK":0.0,"TO":0.0,"PF":0.0,"PTS":0.0,"PLUS_MINUS":-5.0},{"GAME_ID":"0029600244","TEAM_ID":1610612746,"TEAM_ABBREVIATION":"LAC","TEAM_CITY":"Los Angeles","PLAYER_ID":914,"PLAYER_NAME":"Stanley Roberts","NICKNAME":"Stanley","START_POSITION":"","COMMENT":"DNT- Ruptured Disk","MIN":null,"FGM":null,"FGA":null,"FG_PCT":null,"FG3M":null,"FG3A":null,"FG3_PCT":null,"FTM":null,"FTA":null,"FT_PCT":null,"OREB":null,"DREB":null,"REB":null,"AST":null,"STL":null,"BLK":null,"TO":null,"PF":null,"PTS":null,"PLUS_MINUS":null},{"GAME_ID":"0029600244","TEAM_ID":1610612746,"TEAM_ABBREVIATION":"LAC","TEAM_CITY":"Los Angeles","PLAYER_ID":907,"PLAYER_NAME":"Malik Sealy","NICKNAME":"Malik","START_POSITION":"","COMMENT":"DNP - Coach's Decision","MIN":null,"FGM":null,"FGA":null,"FG_PCT":null,"FG3M":null,"FG3A":null,"FG3_PCT":null,"FTM":null,"FTA":null,"FT_PCT":null,"OREB":null,"DREB":null,"REB":null,"AST":null,"STL":null,"BLK":null,"TO":null,"PF":null,"PTS":null,"PLUS_MINUS":null},{"GAME_ID":"0029600244","TEAM_ID":1610612741,"TEAM_ABBREVIATION":"CHI","TEAM_CITY":"Chicago","PLAYER_ID":937,"PLAYER_NAME":"Scottie Pippen","NICKNAME":"Scottie","START_POSITION":"F","COMMENT":"","MIN":"31:47","FGM":12.0,"FGA":23.0,"FG_PCT":0.522,"FG3M":1.0,"FG3A":3.0,"FG3_PCT":0.333,"FTM":0.0,"FTA":1.0,"FT_PCT":0.0,"OREB":4.0,"DREB":4.0,"REB":8.0,"AST":5.0,"STL":4.0,"BLK":0.0,"TO":2.0,"PF":0.0,"PTS":25.0,"PLUS_MINUS":2.0},{"GAME_ID":"0029600244","TEAM_ID":1610612741,"TEAM_ABBREVIATION":"CHI","TEAM_CITY":"Chicago","PLAYER_ID":23,"PLAYER_NAME":"Dennis Rodman","NICKNAME":"Dennis","START_POSITION":"F","COMMENT":"","MIN":"39:22","FGM":0.0,"FGA":3.0,"FG_PCT":0.0,"FG3M":0.0,"FG3A":0.0,"FG3_PCT":0.0,"FTM":0.0,"FTA":0.0,"FT_PCT":0.0,"OREB":7.0,"DREB":7.0,"REB":14.0,"AST":3.0,"STL":0.0,"BLK":0.0,"TO":2.0,"PF":4.0,"PTS":0.0,"PLUS_MINUS":24.0},{"GAME_ID":"0029600244","TEAM_ID":1610612741,"TEAM_ABBREVIATION":"CHI","TEAM_CITY":"Chicago","PLAYER_ID":82,"PLAYER_NAME":"Bill Wennington","NICKNAME":"Bill","START_POSITION":"C","COMMENT":"","MIN":"20:52","FGM":0.0,"FGA":4.0,"FG_PCT":0.0,"FG3M":0.0,"FG3A":0.0,"FG3_PCT":0.0,"FTM":0.0,"FTA":0.0,"FT_PCT":0.0,"OREB":1.0,"DREB":4.0,"REB":5.0,"AST":2.0,"STL":0.0,"BLK":0.0,"TO":0.0,"PF":4.0,"PTS":0.0,"PLUS_MINUS":6.0},{"GAME_ID":"0029600244","TEAM_ID":1610612741,"TEAM_ABBREVIATION":"CHI","TEAM_CITY":"Chicago","PLAYER_ID":389,"PLAYER_NAME":"Toni Kukoc","NICKNAME":"Toni","START_POSITION":"G","COMMENT":"","MIN":"38:24","FGM":7.0,"FGA":14.0,"FG_PCT":0.5,"FG3M":1.0,"FG3A":1.0,"FG3_PCT":1.0,"FTM":3.0,"FTA":3.0,"FT_PCT":1.0,"OREB":2.0,"DREB":3.0,"REB":5.0,"AST":12.0,"STL":0.0,"BLK":1.0,"TO":1.0,"PF":1.0,"PTS":18.0,"PLUS_MINUS":14.0},{"GAME_ID":"0029600244","TEAM_ID":1610612741,"TEAM_ABBREVIATION":"CHI","TEAM_CITY":"Chicago","PLAYER_ID":893,"PLAYER_NAME":"Michael Jordan","NICKNAME":"Michael","START_POSITION":"G","COMMENT":"","MIN":"31:25","FGM":9.0,"FGA":21.0,"FG_PCT":0.429,"FG3M":0.0,"FG3A":3.0,"FG3_PCT":0.0,"FTM":2.0,"FTA":3.0,"FT_PCT":0.667,"OREB":1.0,"DREB":3.0,"REB":4.0,"AST":6.0,"STL":2.0,"BLK":0.0,"TO":1.0,"PF":3.0,"PTS":20.0,"PLUS_MINUS":7.0},{"GAME_ID":"0029600244","TEAM_ID":1610612741,"TEAM_ABBREVIATION":"CHI","TEAM_CITY":"Chicago","PLAYER_ID":146,"PLAYER_NAME":"Jud Buechler","NICKNAME":"Jud","START_POSITION":"","COMMENT":"","MIN":"2:06","FGM":0.0,"FGA":1.0,"FG_PCT":0.0,"FG3M":0.0,"FG3A":0.0,"FG3_PCT":0.0,"FTM":0.0,"FTA":0.0,"FT_PCT":0.0,"OREB":0.0,"DREB":0.0,"REB":0.0,"AST":1.0,"STL":0.0,"BLK":0.0,"TO":1.0,"PF":0.0,"PTS":0.0,"PLUS_MINUS":0.0},{"GAME_ID":"0029600244","TEAM_ID":1610612741,"TEAM_ABBREVIATION":"CHI","TEAM_CITY":"Chicago","PLAYER_ID":70,"PLAYER_NAME":"Steve Kerr","NICKNAME":"Steve","START_POSITION":"","COMMENT":"","MIN":"30:00","FGM":7.0,"FGA":8.0,"FG_PCT":0.875,"FG3M":1.0,"FG3A":2.0,"FG3_PCT":0.5,"FTM":0.0,"FTA":0.0,"FT_PCT":0.0,"OREB":0.0,"DREB":3.0,"REB":3.0,"AST":6.0,"STL":1.0,"BLK":0.0,"TO":0.0,"PF":0.0,"PTS":15.0,"PLUS_MINUS":13.0},{"GAME_ID":"0029600244","TEAM_ID":1610612741,"TEAM_ABBREVIATION":"CHI","TEAM_CITY":"Chicago","PLAYER_ID":679,"PLAYER_NAME":"Jason Caffey","NICKNAME":"Jason","START_POSITION":"","COMMENT":"","MIN":"23:56","FGM":11.0,"FGA":13.0,"FG_PCT":0.846,"FG3M":0.0,"FG3A":0.0,"FG3_PCT":0.0,"FTM":1.0,"FTA":1.0,"FT_PCT":1.0,"OREB":0.0,"DREB":3.0,"REB":3.0,"AST":1.0,"STL":1.0,"BLK":0.0,"TO":3.0,"PF":2.0,"PTS":23.0,"PLUS_MINUS":9.0},{"GAME_ID":"0029600244","TEAM_ID":1610612741,"TEAM_ABBREVIATION":"CHI","TEAM_CITY":"Chicago","PLAYER_ID":753,"PLAYER_NAME":"Randy Brown","NICKNAME":"Randy","START_POSITION":"","COMMENT":"","MIN":"20:28","FGM":6.0,"FGA":8.0,"FG_PCT":0.75,"FG3M":0.0,"FG3A":0.0,"FG3_PCT":0.0,"FTM":1.0,"FTA":2.0,"FT_PCT":0.5,"OREB":0.0,"DREB":1.0,"REB":1.0,"AST":4.0,"STL":2.0,"BLK":0.0,"TO":0.0,"PF":2.0,"PTS":13.0,"PLUS_MINUS":14.0},{"GAME_ID":"0029600244","TEAM_ID":1610612741,"TEAM_ABBREVIATION":"CHI","TEAM_CITY":"Chicago","PLAYER_ID":54,"PLAYER_NAME":"Dickey Simpkins","NICKNAME":"Dickey","START_POSITION":"","COMMENT":"","MIN":"1:41","FGM":0.0,"FGA":0.0,"FG_PCT":0.0,"FG3M":0.0,"FG3A":0.0,"FG3_PCT":0.0,"FTM":0.0,"FTA":0.0,"FT_PCT":0.0,"OREB":0.0,"DREB":0.0,"REB":0.0,"AST":0.0,"STL":0.0,"BLK":0.0,"TO":0.0,"PF":0.0,"PTS":0.0,"PLUS_MINUS":1.0},{"GAME_ID":"0029600244","TEAM_ID":1610612741,"TEAM_ABBREVIATION":"CHI","TEAM_CITY":"Chicago","PLAYER_ID":166,"PLAYER_NAME":"Ron Harper","NICKNAME":"Ron","START_POSITION":"","COMMENT":"DND- Flu","MIN":null,"FGM":null,"FGA":null,"FG_PCT":null,"FG3M":null,"FG3A":null,"FG3_PCT":null,"FTM":null,"FTA":null,"FT_PCT":null,"OREB":null,"DREB":null,"REB":null,"AST":null,"STL":null,"BLK":null,"TO":null,"PF":null,"PTS":null,"PLUS_MINUS":null},{"GAME_ID":"0029600244","TEAM_ID":1610612741,"TEAM_ABBREVIATION":"CHI","TEAM_CITY":"Chicago","PLAYER_ID":305,"PLAYER_NAME":"Robert Parish","NICKNAME":"Robert","START_POSITION":"","COMMENT":"DNP - Coach's Decision","MIN":null,"FGM":null,"FGA":null,"FG_PCT":null,"FG3M":null,"FG3A":null,"FG3_PCT":null,"FTM":null,"FTA":null,"FT_PCT":null,"OREB":null,"DREB":null,"REB":null,"AST":null,"STL":null,"BLK":null,"TO":null,"PF":null,"PTS":null,"PLUS_MINUS":null}]