[{"GAME_ID":"0029500920","TEAM_ID":1610612751,"TEAM_ABBREVIATION":"NJN","TEAM_CITY":"New Jersey","PLAYER_ID":288,"PLAYER_NAME":"Armen Gilliam","NICKNAME":"Armen","START_POSITION":"","COMMENT":"","MIN":39,"FGM":7,"FGA":16,"FG_PCT":0.438,"FG3M":0,"FG3A":0,"FG3_PCT":0.0,"FTM":7,"FTA":8,"FT_PCT":0.875,"OREB":3,"DREB":6.0,"REB":9.0,"AST":2,"STL":1,"BLK":1,"TO":4,"PF":3,"PTS":21,"PLUS_MINUS":null},{"GAME_ID":"0029500920","TEAM_ID":1610612751,"TEAM_ABBREVIATION":"NJN","TEAM_CITY":"New Jersey","PLAYER_ID":164,"PLAYER_NAME":"Chris Childs","NICKNAME":"Chris","START_POSITION":"","COMMENT":"","MIN":44,"FGM":6,"FGA":17,"FG_PCT":0.352,"FG3M":2,"FG3A":5,"FG3_PCT":0.4,"FTM":4,"FTA":5,"FT_PCT":0.8,"OREB":1,"DREB":9.0,"REB":10.0,"AST":14,"STL":1,"BLK":1,"TO":4,"PF":4,"PTS":18,"PLUS_MINUS":null},{"GAME_ID":"0029500920","TEAM_ID":1610612751,"TEAM_ABBREVIATION":"NJN","TEAM_CITY":"New Jersey","PLAYER_ID":77741,"PLAYER_NAME":"Ed O'Bannon","NICKNAME":"Ed","START_POSITION":"","COMMENT":"","MIN":21,"FGM":2,"FGA":5,"FG_PCT":0.4,"FG3M":0,"FG3A":0,"FG3_PCT":0.0,"FTM":3,"FTA":5,"FT_PCT":0.599,"OREB":0,"DREB":null,"REB":null,"AST":0,"STL":0,"BLK":0,"TO":0,"PF":3,"PTS":7,"PLUS_MINUS":null},{"GAME_ID":"0029500920","TEAM_ID":1610612751,"TEAM_ABBREVIATION":"NJN","TEAM_CITY":"New Jersey","PLAYER_ID":37,"PLAYER_NAME":"Greg Graham","NICKNAME":"Greg","START_POSITION":"","COMMENT":"","MIN":5,"FGM":0,"FGA":1,"FG_PCT":0.0,"FG3M":0,"FG3A":0,"FG3_PCT":0.0,"FTM":0,"FTA":0,"FT_PCT":0.0,"OREB":0,"DREB":0.0,"REB":0.0,"AST":0,"STL":0,"BLK":0,"TO":0,"PF":0,"PTS":0,"PLUS_MINUS":null},{"GAME_ID":"0029500920","TEAM_ID":1610612751,"TEAM_ABBREVIATION":"NJN","TEAM_CITY":"New Jersey","PLAYER_ID":420,"PLAYER_NAME":"Jayson Williams","NICKNAME":"Jayson","START_POSITION":"","COMMENT":"","MIN":18,"FGM":2,"FGA":5,"FG_PCT":0.4,"FG3M":0,"FG3A":0,"FG3_PCT":0.0,"FTM":1,"FTA":4,"FT_PCT":0.25,"OREB":4,"DREB":9.0,"REB":13.0,"AST":0,"STL":0,"BLK":1,"TO":1,"PF":4,"PTS":5,"PLUS_MINUS":null},{"GAME_ID":"0029500920","TEAM_ID":1610612751,"TEAM_ABBREVIATION":"NJN","TEAM_CITY":"New Jersey","PLAYER_ID":234,"PLAYER_NAME":"Khalid Reeves","NICKNAME":"Khalid","START_POSITION":"","COMMENT":"","MIN":2,"FGM":0,"FGA":0,"FG_PCT":0.0,"FG3M":0,"FG3A":0,"FG3_PCT":0.0,"FTM":0,"FTA":0,"FT_PCT":0.0,"OREB":0,"DREB":0.0,"REB":0.0,"AST":0,"STL":0,"BLK":0,"TO":0,"PF":0,"PTS":0,"PLUS_MINUS":null},{"GAME_ID":"0029500920","TEAM_ID":1610612751,"TEAM_ABBREVIATION":"NJN","TEAM_CITY":"New Jersey","PLAYER_ID":136,"PLAYER_NAME":"P.J. Brown","NICKNAME":"P.J.","START_POSITION":"","COMMENT":"","MIN":37,"FGM":6,"FGA":11,"FG_PCT":0.545,"FG3M":0,"FG3A":0,"FG3_PCT":0.0,"FTM":3,"FTA":3,"FT_PCT":1.0,"OREB":4,"DREB":4.0,"REB":8.0,"AST":1,"STL":0,"BLK":0,"TO":1,"PF":2,"PTS":15,"PLUS_MINUS":null},{"GAME_ID":"0029500920","TEAM_ID":1610612751,"TEAM_ABBREVIATION":"NJN","TEAM_CITY":"New Jersey","PLAYER_ID":328,"PLAYER_NAME":"Rick Mahorn","NICKNAME":"Rick","START_POSITION":"","COMMENT":"","MIN":8,"FGM":0,"FGA":4,"FG_PCT":0.0,"FG3M":0,"FG3A":0,"FG3_PCT":0.0,"FTM":0,"FTA":0,"FT_PCT":0.0,"OREB":2,"DREB":0.0,"REB":2.0,"AST":0,"STL":0,"BLK":1,"TO":1,"PF":2,"PTS":0,"PLUS_MINUS":null},{"GAME_ID":"0029500920","TEAM_ID":1610612751,"TEAM_ABBREVIATION":"NJN","TEAM_CITY":"New Jersey","PLAYER_ID":762,"PLAYER_NAME":"Shawn Bradley","NICKNAME":"Shawn","START_POSITION":"","COMMENT":"","MIN":36,"FGM":4,"FGA":15,"FG_PCT":0.267,"FG3M":0,"FG3A":0,"FG3_PCT":0.0,"FTM":9,"FTA":11,"FT_PCT":0.817,"OREB":7,"DREB":5.0,"REB":12.0,"AST":0,"STL":1,"BLK":6,"TO":1,"PF":4,"PTS":17,"PLUS_MINUS":null},{"GAME_ID":"0029500920","TEAM_ID":1610612751,"TEAM_ABBREVIATION":"NJN","TEAM_CITY":"New Jersey","PLAYER_ID":313,"PLAYER_NAME":"Vern Fleming","NICKNAME":"Vern","START_POSITION":"","COMMENT":"","MIN":30,"FGM":5,"FGA":10,"FG_PCT":0.5,"FG3M":0,"FG3A":0,"FG3_PCT":0.0,"FTM":0,"FTA":1,"FT_PCT":0.0,"OREB":1,"DREB":3.0,"REB":4.0,"AST":4,"STL":0,"BLK":0,"TO":1,"PF":2,"PTS":10,"PLUS_MINUS":null},{"GAME_ID":"0029500920","TEAM_ID":1610612741,"TEAM_ABBREVIATION":"CHI","TEAM_CITY":"Chicago","PLAYER_ID":82,"PLAYER_NAME":"Bill Wennington","NICKNAME":"Bill","START_POSITION":"","COMMENT":"","MIN":20,"FGM":4,"FGA":10,"FG_PCT":0.4,"FG3M":0,"FG3A":0,"FG3_PCT":0.0,"FTM":0,"FTA":0,"FT_PCT":0.0,"OREB":5,"DREB":1.0,"REB":6.0,"AST":0,"STL":0,"BLK":1,"TO":0,"PF":4,"PTS":8,"PLUS_MINUS":null},{"GAME_ID":"0029500920","TEAM_ID":1610612741,"TEAM_ABBREVIATION":"CHI","TEAM_CITY":"Chicago","PLAYER_ID":23,"PLAYER_NAME":"Dennis Rodman","NICKNAME":"Dennis","START_POSITION":"","COMMENT":"","MIN":10,"FGM":0,"FGA":0,"FG_PCT":0.0,"FG3M":0,"FG3A":0,"FG3_PCT":0.0,"FTM":0,"FTA":0,"FT_PCT":0.0,"OREB":0,"DREB":4.0,"REB":4.0,"AST":3,"STL":0,"BLK":0,"TO":2,"PF":1,"PTS":0,"PLUS_MINUS":null},{"GAME_ID":"0029500920","TEAM_ID":1610612741,"TEAM_ABBREVIATION":"CHI","TEAM_CITY":"Chicago","PLAYER_ID":229,"PLAYER_NAME":"James Edwards","NICKNAME":"James","START_POSITION":"","COMMENT":"","MIN":4,"FGM":0,"FGA":0,"FG_PCT":0.0,"FG3M":0,"FG3A":0,"FG3_PCT":0.0,"FTM":0,"FTA":0,"FT_PCT":0.0,"OREB":0,"DREB":0.0,"REB":0.0,"AST":1,"STL":0,"BLK":0,"TO":0,"PF":0,"PTS":0,"PLUS_MINUS":null},{"GAME_ID":"0029500920","TEAM_ID":1610612741,"TEAM_ABBREVIATION":"CHI","TEAM_CITY":"Chicago","PLAYER_ID":927,"PLAYER_NAME":"John Salley","NICKNAME":"John","START_POSITION":"","COMMENT":"","MIN":11,"FGM":1,"FGA":3,"FG_PCT":0.333,"FG3M":0,"FG3A":0,"FG3_PCT":0.0,"FTM":0,"FTA":0,"FT_PCT":0.0,"OREB":2,"DREB":3.0,"REB":5.0,"AST":0,"STL":0,"BLK":1,"TO":0,"PF":1,"PTS":2,"PLUS_MINUS":null},{"GAME_ID":"0029500920","TEAM_ID":1610612741,"TEAM_ABBREVIATION":"CHI","TEAM_CITY":"Chicago","PLAYER_ID":146,"PLAYER_NAME":"Jud Buechler","NICKNAME":"Jud","START_POSITION":"","COMMENT":"","MIN":14,"FGM":4,"FGA":7,"FG_PCT":0.57,"FG3M":3,"FG3A":5,"FG3_PCT":0.599,"FTM":0,"FTA":0,"FT_PCT":0.0,"OREB":0,"DREB":1.0,"REB":1.0,"AST":1,"STL":2,"BLK":0,"TO":0,"PF":2,"PTS":11,"PLUS_MINUS":null},{"GAME_ID":"0029500920","TEAM_ID":1610612741,"TEAM_ABBREVIATION":"CHI","TEAM_CITY":"Chicago","PLAYER_ID":26,"PLAYER_NAME":"Luc Longley","NICKNAME":"Luc","START_POSITION":"","COMMENT":"","MIN":28,"FGM":1,"FGA":9,"FG_PCT":0.111,"FG3M":0,"FG3A":0,"FG3_PCT":0.0,"FTM":0,"FTA":0,"FT_PCT":0.0,"OREB":1,"DREB":5.0,"REB":6.0,"AST":3,"STL":0,"BLK":2,"TO":0,"PF":5,"PTS":2,"PLUS_MINUS":null},{"GAME_ID":"0029500920","TEAM_ID":1610612741,"TEAM_ABBREVIATION":"CHI","TEAM_CITY":"Chicago","PLAYER_ID":893,"PLAYER_NAME":"Michael Jordan","NICKNAME":"Michael","START_POSITION":"","COMMENT":"","MIN":43,"FGM":14,"FGA":29,"FG_PCT":0.482,"FG3M":2,"FG3A":5,"FG3_PCT":0.4,"FTM":7,"FTA":7,"FT_PCT":1.0,"OREB":2,"DREB":14.0,"REB":16.0,"AST":5,"STL":1,"BLK":3,"TO":0,"PF":4,"PTS":37,"PLUS_MINUS":null},{"GAME_ID":"0029500920","TEAM_ID":1610612741,"TEAM_ABBREVIATION":"CHI","TEAM_CITY":"Chicago","PLAYER_ID":753,"PLAYER_NAME":"Randy Brown","NICKNAME":"Randy","START_POSITION":"","COMMENT":"","MIN":3,"FGM":0,"FGA":0,"FG_PCT":0.0,"FG3M":0,"FG3A":0,"FG3_PCT":0.0,"FTM":0,"FTA":0,"FT_PCT":0.0,"OREB":0,"DREB":0.0,"REB":0.0,"AST":0,"STL":0,"BLK":0,"TO":1,"PF":0,"PTS":0,"PLUS_MINUS":null},{"GAME_ID":"0029500920","TEAM_ID":1610612741,"TEAM_ABBREVIATION":"CHI","TEAM_CITY":"Chicago","PLAYER_ID":166,"PLAYER_NAME":"Ron Harper","NICKNAME":"Ron","START_POSITION":"","COMMENT":"","MIN":39,"FGM":4,"FGA":8,"FG_PCT":0.5,"FG3M":0,"FG3A":0,"FG3_PCT":0.0,"FTM":1,"FTA":2,"FT_PCT":0.5,"OREB":2,"DREB":1.0,"REB":3.0,"AST":1,"STL":2,"BLK":1,"TO":2,"PF":3,"PTS":9,"PLUS_MINUS":null},{"GAME_ID":"0029500920","TEAM_ID":1610612741,"TEAM_ABBREVIATION":"CHI","TEAM_CITY":"Chicago","PLAYER_ID":70,"PLAYER_NAME":"Steve Kerr","NICKNAME":"Steve","START_POSITION":"","COMMENT":"","MIN":30,"FGM":4,"FGA":7,"FG_PCT":0.57,"FG3M":2,"FG3A":4,"FG3_PCT":0.5,"FTM":0,"FTA":0,"FT_PCT":0.0,"OREB":0,"DREB":0.0,"REB":0.0,"AST":2,"STL":0,"BLK":0,"TO":2,"PF":0,"PTS":10,"PLUS_MINUS":null},{"GAME_ID":"0029500920","TEAM_ID":1610612741,"TEAM_ABBREVIATION":"CHI","TEAM_CITY":"Chicago","PLAYER_ID":389,"PLAYER_NAME":"Toni Kukoc","NICKNAME":"Toni","START_POSITION":"","COMMENT":"","MIN":38,"FGM":5,"FGA":16,"FG_PCT":0.313,"FG3M":0,"FG3A":5,"FG3_PCT":0.0,"FTM":8,"FTA":10,"FT_PCT":0.8,"OREB":3,"DREB":3.0,"REB":6.0,"AST":4,"STL":0,"BLK":1,"TO":1,"PF":5,"PTS":18,"PLUS_MINUS":null}]