[{"GAME_ID":"0029600199","TEAM_ID":1610612745,"TEAM_ABBREVIATION":"HOU","TEAM_CITY":"Houston","PLAYER_ID":787,"PLAYER_NAME":"Charles Barkley","NICKNAME":"Charles","START_POSITION":"F","COMMENT":"","MIN":"30:13","FGM":7.0,"FGA":9.0,"FG_PCT":0.778,"FG3M":3.0,"FG3A":4.0,"FG3_PCT":0.75,"FTM":1.0,"FTA":2.0,"FT_PCT":0.5,"OREB":2.0,"DREB":7.0,"REB":9.0,"AST":2.0,"STL":1.0,"BLK":1.0,"TO":2.0,"PF":1.0,"PTS":18.0,"PLUS_MINUS":18.0},{"GAME_ID":"0029600199","TEAM_ID":1610612745,"TEAM_ABBREVIATION":"HOU","TEAM_CITY":"Houston","PLAYER_ID":53,"PLAYER_NAME":"Mario Elie","NICKNAME":"Mario","START_POSITION":"F","COMMENT":"","MIN":"24:00","FGM":3.0,"FGA":4.0,"FG_PCT":0.75,"FG3M":2.0,"FG3A":3.0,"FG3_PCT":0.667,"FTM":2.0,"FTA":2.0,"FT_PCT":1.0,"OREB":0.0,"DREB":1.0,"REB":1.0,"AST":8.0,"STL":1.0,"BLK":1.0,"TO":4.0,"PF":0.0,"PTS":10.0,"PLUS_MINUS":24.0},{"GAME_ID":"0029600199","TEAM_ID":1610612745,"TEAM_ABBREVIATION":"HOU","TEAM_CITY":"Houston","PLAYER_ID":165,"PLAYER_NAME":"Hakeem Olajuwon","NICKNAME":"Hakeem","START_POSITION":"C","COMMENT":"","MIN":"28:05","FGM":8.0,"FGA":16.0,"FG_PCT":0.5,"FG3M":0.0,"FG3A":0.0,"FG3_PCT":0.0,"FTM":1.0,"FTA":2.0,"FT_PCT":0.5,"OREB":3.0,"DREB":10.0,"REB":13.0,"AST":3.0,"STL":0.0,"BLK":0.0,"TO":3.0,"PF":3.0,"PTS":17.0,"PLUS_MINUS":20.0},{"GAME_ID":"0029600199","TEAM_ID":1610612745,"TEAM_ABBREVIATION":"HOU","TEAM_CITY":"Houston","PLAYER_ID":1074,"PLAYER_NAME":"Matt Maloney","NICKNAME":"Matt","START_POSITION":"G","COMMENT":"","MIN":"26:39","FGM":6.0,"FGA":8.0,"FG_PCT":0.75,"FG3M":3.0,"FG3A":4.0,"FG3_PCT":0.75,"FTM":3.0,"FTA":3.0,"FT_PCT":1.0,"OREB":0.0,"DREB":3.0,"REB":3.0,"AST":2.0,"STL":2.0,"BLK":0.0,"TO":1.0,"PF":1.0,"PTS":18.0,"PLUS_MINUS":19.0},{"GAME_ID":"0029600199","TEAM_ID":1610612745,"TEAM_ABBREVIATION":"HOU","TEAM_CITY":"Houston","PLAYER_ID":17,"PLAYER_NAME":"Clyde Drexler","NICKNAME":"Clyde","START_POSITION":"G","COMMENT":"","MIN":"24:00","FGM":6.0,"FGA":9.0,"FG_PCT":0.667,"FG3M":1.0,"FG3A":3.0,"FG3_PCT":0.333,"FTM":2.0,"FTA":2.0,"FT_PCT":1.0,"OREB":1.0,"DREB":3.0,"REB":4.0,"AST":5.0,"STL":0.0,"BLK":0.0,"TO":1.0,"PF":0.0,"PTS":15.0,"PLUS_MINUS":24.0},{"GAME_ID":"0029600199","TEAM_ID":1610612745,"TEAM_ABBREVIATION":"HOU","TEAM_CITY":"Houston","PLAYER_ID":788,"PLAYER_NAME":"Kevin Willis","NICKNAME":"Kevin","START_POSITION":"","COMMENT":"","MIN":"27:09","FGM":5.0,"FGA":10.0,"FG_PCT":0.5,"FG3M":1.0,"FG3A":1.0,"FG3_PCT":1.0,"FTM":1.0,"FTA":2.0,"FT_PCT":0.5,"OREB":3.0,"DREB":7.0,"REB":10.0,"AST":2.0,"STL":0.0,"BLK":0.0,"TO":3.0,"PF":4.0,"PTS":12.0,"PLUS_MINUS":12.0},{"GAME_ID":"0029600199","TEAM_ID":1610612745,"TEAM_ABBREVIATION":"HOU","TEAM_CITY":"Houston","PLAYER_ID":988,"PLAYER_NAME":"Randy Livingston","NICKNAME":"Randy","START_POSITION":"","COMMENT":"","MIN":"21:21","FGM":2.0,"FGA":4.0,"FG_PCT":0.5,"FG3M":0.0,"FG3A":1.0,"FG3_PCT":0.0,"FTM":6.0,"FTA":6.0,"FT_PCT":1.0,"OREB":2.0,"DREB":2.0,"REB":4.0,"AST":4.0,"STL":1.0,"BLK":0.0,"TO":2.0,"PF":2.0,"PTS":10.0,"PLUS_MINUS":7.0},{"GAME_ID":"0029600199","TEAM_ID":1610612745,"TEAM_ABBREVIATION":"HOU","TEAM_CITY":"Houston","PLAYER_ID":672,"PLAYER_NAME":"Matt Bullard","NICKNAME":"Matt","START_POSITION":"","COMMENT":"","MIN":"18:22","FGM":3.0,"FGA":6.0,"FG_PCT":0.5,"FG3M":2.0,"FG3A":4.0,"FG3_PCT":0.5,"FTM":0.0,"FTA":0.0,"FT_PCT":0.0,"OREB":0.0,"DREB":0.0,"REB":0.0,"AST":3.0,"STL":0.0,"BLK":0.0,"TO":0.0,"PF":2.0,"PTS":8.0,"PLUS_MINUS":5.0},{"GAME_ID":"0029600199","TEAM_ID":1610612745,"TEAM_ABBREVIATION":"HOU","TEAM_CITY":"Houston","PLAYER_ID":929,"PLAYER_NAME":"Tracy Moore","NICKNAME":"Tracy","START_POSITION":"","COMMENT":"","MIN":"24:00","FGM":4.0,"FGA":7.0,"FG_PCT":0.571,"FG3M":0.0,"FG3A":1.0,"FG3_PCT":0.0,"FTM":1.0,"FTA":2.0,"FT_PCT":0.5,"OREB":2.0,"DREB":2.0,"REB":4.0,"AST":1.0,"STL":0.0,"BLK":0.0,"TO":2.0,"PF":2.0,"PTS":9.0,"PLUS_MINUS":2.0},{"GAME_ID":"0029600199","TEAM_ID":1610612745,"TEAM_ABBREVIATION":"HOU","TEAM_CITY":"Houston","PLAYER_ID":970,"PLAYER_NAME":"Othella Harrington","NICKNAME":"Othella","START_POSITION":"","COMMENT":"","MIN":"10:33","FGM":1.0,"FGA":4.0,"FG_PCT":0.25,"FG3M":0.0,"FG3A":0.0,"FG3_PCT":0.0,"FTM":1.0,"FTA":4.0,"FT_PCT":0.25,"OREB":1.0,"DREB":1.0,"REB":2.0,"AST":0.0,"STL":0.0,"BLK":1.0,"TO":1.0,"PF":1.0,"PTS":3.0,"PLUS_MINUS":2.0},{"GAME_ID":"0029600199","TEAM_ID":1610612745,"TEAM_ABBREVIATION":"HOU","TEAM_CITY":"Houston","PLAYER_ID":1120,"PLAYER_NAME":"Elmer Bennett","NICKNAME":"Elmer","START_POSITION":"","COMMENT":"","MIN":"5:38","FGM":0.0,"FGA":3.0,"FG_PCT":0.0,"FG3M":0.0,"FG3A":1.0,"FG3_PCT":0.0,"FTM":0.0,"FTA":0.0,"FT_PCT":0.0,"OREB":0.0,"DREB":1.0,"REB":1.0,"AST":0.0,"STL":0.0,"BLK":0.0,"TO":0.0,"PF":0.0,"PTS":0.0,"PLUS_MINUS":-3.0},{"GAME_ID":"0029600199","TEAM_ID":1610612745,"TEAM_ABBREVIATION":"HOU","TEAM_CITY":"Houston","PLAYER_ID":694,"PLAYER_NAME":"Sam Mack","NICKNAME":"Sam","START_POSITION":"","COMMENT":"NWT - Sprained Left Foot","MIN":null,"FGM":null,"FGA":null,"FG_PCT":null,"FG3M":null,"FG3A":null,"FG3_PCT":null,"FTM":null,"FTA":null,"FT_PCT":null,"OREB":null,"DREB":null,"REB":null,"AST":null,"STL":null,"BLK":null,"TO":null,"PF":null,"PTS":null,"PLUS_MINUS":null},{"GAME_ID":"0029600199","TEAM_ID":1610612738,"TEAM_ABBREVIATION":"BOS","TEAM_CITY":"Boston","PLAYER_ID":952,"PLAYER_NAME":"Antoine Walker","NICKNAME":"Antoine","START_POSITION":"F","COMMENT":"","MIN":"26:30","FGM":5.0,"FGA":15.0,"FG_PCT":0.333,"FG3M":0.0,"FG3A":2.0,"FG3_PCT":0.0,"FTM":2.0,"FTA":3.0,"FT_PCT":0.667,"OREB":3.0,"DREB":4.0,"REB":7.0,"AST":3.0,"STL":2.0,"BLK":0.0,"TO":1.0,"PF":1.0,"PTS":12.0,"PLUS_MINUS":-14.0},{"GAME_ID":"0029600199","TEAM_ID":1610612738,"TEAM_ABBREVIATION":"BOS","TEAM_CITY":"Boston","PLAYER_ID":677,"PLAYER_NAME":"Eric Williams","NICKNAME":"Eric","START_POSITION":"F","COMMENT":"","MIN":"23:28","FGM":2.0,"FGA":7.0,"FG_PCT":0.286,"FG3M":0.0,"FG3A":0.0,"FG3_PCT":0.0,"FTM":0.0,"FTA":0.0,"FT_PCT":0.0,"OREB":1.0,"DREB":3.0,"REB":4.0,"AST":1.0,"STL":0.0,"BLK":0.0,"TO":1.0,"PF":2.0,"PTS":4.0,"PLUS_MINUS":-21.0},{"GAME_ID":"0029600199","TEAM_ID":1610612738,"TEAM_ABBREVIATION":"BOS","TEAM_CITY":"Boston","PLAYER_ID":129,"PLAYER_NAME":"Dino Radja","NICKNAME":"Dino","START_POSITION":"C","COMMENT":"","MIN":"27:01","FGM":8.0,"FGA":13.0,"FG_PCT":0.615,"FG3M":0.0,"FG3A":0.0,"FG3_PCT":0.0,"FTM":2.0,"FTA":2.0,"FT_PCT":1.0,"OREB":1.0,"DREB":2.0,"REB":3.0,"AST":1.0,"STL":0.0,"BLK":0.0,"TO":2.0,"PF":3.0,"PTS":18.0,"PLUS_MINUS":-20.0},{"GAME_ID":"0029600199","TEAM_ID":1610612738,"TEAM_ABBREVIATION":"BOS","TEAM_CITY":"Boston","PLAYER_ID":344,"PLAYER_NAME":"Dana Barros","NICKNAME":"Dana","START_POSITION":"G","COMMENT":"","MIN":"31:45","FGM":5.0,"FGA":13.0,"FG_PCT":0.385,"FG3M":1.0,"FG3A":4.0,"FG3_PCT":0.25,"FTM":3.0,"FTA":4.0,"FT_PCT":0.75,"OREB":1.0,"DREB":1.0,"REB":2.0,"AST":2.0,"STL":1.0,"BLK":0.0,"TO":2.0,"PF":1.0,"PTS":14.0,"PLUS_MINUS":-22.0},{"GAME_ID":"0029600199","TEAM_ID":1610612738,"TEAM_ABBREVIATION":"BOS","TEAM_CITY":"Boston","PLAYER_ID":296,"PLAYER_NAME":"Rick Fox","NICKNAME":"Rick","START_POSITION":"G","COMMENT":"","MIN":"27:05","FGM":4.0,"FGA":11.0,"FG_PCT":0.364,"FG3M":1.0,"FG3A":4.0,"FG3_PCT":0.25,"FTM":0.0,"FTA":0.0,"FT_PCT":0.0,"OREB":2.0,"DREB":2.0,"REB":4.0,"AST":3.0,"STL":4.0,"BLK":1.0,"TO":1.0,"PF":2.0,"PTS":9.0,"PLUS_MINUS":-17.0},{"GAME_ID":"0029600199","TEAM_ID":1610612738,"TEAM_ABBREVIATION":"BOS","TEAM_CITY":"Boston","PLAYER_ID":244,"PLAYER_NAME":"Dee Brown","NICKNAME":"Dee","START_POSITION":"","COMMENT":"","MIN":"28:33","FGM":5.0,"FGA":10.0,"FG_PCT":0.5,"FG3M":1.0,"FG3A":2.0,"FG3_PCT":0.5,"FTM":0.0,"FTA":0.0,"FT_PCT":0.0,"OREB":0.0,"DREB":2.0,"REB":2.0,"AST":5.0,"STL":1.0,"BLK":0.0,"TO":0.0,"PF":3.0,"PTS":11.0,"PLUS_MINUS":-15.0},{"GAME_ID":"0029600199","TEAM_ID":1610612738,"TEAM_ABBREVIATION":"BOS","TEAM_CITY":"Boston","PLAYER_ID":783,"PLAYER_NAME":"Frank Brickowski","NICKNAME":"Frank","START_POSITION":"","COMMENT":"","MIN":"8:27","FGM":1.0,"FGA":1.0,"FG_PCT":1.0,"FG3M":0.0,"FG3A":0.0,"FG3_PCT":0.0,"FTM":0.0,"FTA":0.0,"FT_PCT":0.0,"OREB":1.0,"DREB":0.0,"REB":1.0,"AST":0.0,"STL":0.0,"BLK":0.0,"TO":0.0,"PF":0.0,"PTS":2.0,"PLUS_MINUS":-12.0},{"GAME_ID":"0029600199","TEAM_ID":1610612738,"TEAM_ABBREVIATION":"BOS","TEAM_CITY":"Boston","PLAYER_ID":103,"PLAYER_NAME":"Todd Day","NICKNAME":"Todd","START_POSITION":"","COMMENT":"","MIN":"21:33","FGM":2.0,"FGA":5.0,"FG_PCT":0.4,"FG3M":1.0,"FG3A":1.0,"FG3_PCT":1.0,"FTM":3.0,"FTA":4.0,"FT_PCT":0.75,"OREB":0.0,"DREB":4.0,"REB":4.0,"AST":0.0,"STL":0.0,"BLK":0.0,"TO":2.0,"PF":4.0,"PTS":8.0,"PLUS_MINUS":-12.0},{"GAME_ID":"0029600199","TEAM_ID":1610612738,"TEAM_ABBREVIATION":"BOS","TEAM_CITY":"Boston","PLAYER_ID":65,"PLAYER_NAME":"Greg Minor","NICKNAME":"Greg","START_POSITION":"","COMMENT":"","MIN":"21:32","FGM":4.0,"FGA":8.0,"FG_PCT":0.5,"FG3M":0.0,"FG3A":0.0,"FG3_PCT":0.0,"FTM":0.0,"FTA":0.0,"FT_PCT":0.0,"OREB":2.0,"DREB":2.0,"REB":4.0,"AST":2.0,"STL":1.0,"BLK":0.0,"TO":0.0,"PF":1.0,"PTS":8.0,"PLUS_MINUS":4.0},{"GAME_ID":"0029600199","TEAM_ID":1610612738,"TEAM_ABBREVIATION":"BOS","TEAM_CITY":"Boston","PLAYER_ID":55,"PLAYER_NAME":"Marty Conlon","NICKNAME":"Marty","START_POSITION":"","COMMENT":"","MIN":"16:20","FGM":2.0,"FGA":5.0,"FG_PCT":0.4,"FG3M":0.0,"FG3A":0.0,"FG3_PCT":0.0,"FTM":1.0,"FTA":2.0,"FT_PCT":0.5,"OREB":1.0,"DREB":0.0,"REB":1.0,"AST":1.0,"STL":0.0,"BLK":0.0,"TO":0.0,"PF":3.0,"PTS":5.0,"PLUS_MINUS":2.0},{"GAME_ID":"0029600199","TEAM_ID":1610612738,"TEAM_ABBREVIATION":"BOS","TEAM_CITY":"Boston","PLAYER_ID":1136,"PLAYER_NAME":"Brett Szabo","NICKNAME":"Brett","START_POSITION":"","COMMENT":"","MIN":"7:46","FGM":1.0,"FGA":3.0,"FG_PCT":0.333,"FG3M":0.0,"FG3A":0.0,"FG3_PCT":0.0,"FTM":1.0,"FTA":2.0,"FT_PCT":0.5,"OREB":0.0,"DREB":1.0,"REB":1.0,"AST":0.0,"STL":0.0,"BLK":1.0,"TO":0.0,"PF":1.0,"PTS":3.0,"PLUS_MINUS":-3.0},{"GAME_ID":"0029600199","TEAM_ID":1610612738,"TEAM_ABBREVIATION":"BOS","TEAM_CITY":"Boston","PLAYER_ID":133,"PLAYER_NAME":"David Wesley","NICKNAME":"David","START_POSITION":"","COMMENT":"DND - Sore Right Foot","MIN":null,"FGM":null,"FGA":null,"FG_PCT":null,"FG3M":null,"FG3A":null,"FG3_PCT":null,"FTM":null,"FTA":null,"FT_PCT":null,"OREB":null,"DREB":null,"REB":null,"AST":null,"STL":null,"BLK":null,"TO":null,"PF":null,"PTS":null,"PLUS_MINUS":null}]